ap_int/__init__.py
ap_int-0.0.1.dist-info/COPYING
ap_int-0.0.1.dist-info/METADATA
ap_int-0.0.1.dist-info/WHEEL
ap_int-0.0.1.dist-info/top_level.txt
ap_int-0.0.1.dist-info/RECORD
